setup.py
PyOLP/__init__.py
PyOLP/api_exceptions.py
PyOLP/api_objects.py
PyOLP/main_class.py
PyOLP/paginated.py
PyOLP/requester.py
PyOLP.egg-info/PKG-INFO
PyOLP.egg-info/SOURCES.txt
PyOLP.egg-info/dependency_links.txt
PyOLP.egg-info/top_level.txt
PyOLP/tests/AllTests.py
PyOLP/tests/__init__.py
PyOLP/tests/price.py
PyOLP/tests/product.py
PyOLP/tests/store.py