Metadata-Version: 1.1
Name: PyOLP
Version: 0.1.1
Summary: Python library implementing the Oregon Liquor Prices V1 API
Home-page: https://github.com/cameronbwhite/PyOLP
Author: Cameron Brandon White
Author-email: cameronbwhite90@gmail.com
License: GPL3
Download-URL: https://github.com/cameronbwhite/PyOLP/downloads
Platform: UNKNOWN
Classifier: Development Status :: 4 - Beta
Classifier: License :: OSI Approved :: GNU General Public License (GPL)
Classifier: Intended Audience :: Developers
Classifier: Operating System :: OS Independent
Classifier: Programming Language :: Python :: 2.7
Classifier: Topic :: Software Development :: Libraries :: Python Modules
Provides: PyOLP
